qrsolv.cpython-310-x86_64-linux-gnu.so
levmarpy/qrsolv.cpython-310-x86_64-linux-gnu.so
marlev/qrsolv.cpython-310-x86_64-linux-gnu.so
marlev-0.1.dist-info/LICENSE
marlev-0.1.dist-info/METADATA
marlev-0.1.dist-info/WHEEL
marlev-0.1.dist-info/top_level.txt
marlev-0.1.dist-info/RECORD
