Metadata-Version: 2.1
Name: marlev
Version: 0.1
Summary: Levenberg-Marquardt fitter
Home-page: UNKNOWN
Author: Martin Teichmann
Author-email: martin.teichmann@xfel.eu
License: UNKNOWN
Platform: UNKNOWN
License-File: LICENSE
